{
  "id": "SV_DE00015552",
  "source": "global",
  "language": "sv",
  "version": 2,
  "headword": {
    "text": "raka",
    "pronunciation": {
      "value": "²rạ:ka"
    },
    "pos": "noun",
    "homograph_number": 1,
    "inflections": [
      {
        "text": "rakan",
        "number": "singular",
        "subcategorization": "determined"
      },
      {
        "text": "rakor",
        "number": "plural",
        "subcategorization": "undetermined"
      },
      {
        "text": "rakorna",
        "number": "plural",
        "subcategorization": "determined"
      }
    ]
  },
  "senses": [
    {
      "id": "SV_SE00018828",
      "definition": "raksträcka",
      "register": "informal",
      "examples": [
        {
          "text": "Vi tog rakan i 150 kmh."
        }
      ]
    }
  ]
}